napari_s3zarr/__init__.py
napari_s3zarr/_version.py
napari_s3zarr/s3zarr.py
napari_s3zarr/_tests/__init__.py
napari_s3zarr/_tests/test_s3zarr.py
napari_s3zarr-0.0.2.dist-info/LICENSE
napari_s3zarr-0.0.2.dist-info/METADATA
napari_s3zarr-0.0.2.dist-info/WHEEL
napari_s3zarr-0.0.2.dist-info/entry_points.txt
napari_s3zarr-0.0.2.dist-info/top_level.txt
napari_s3zarr-0.0.2.dist-info/RECORD
